kiox/__init__.py
kiox/_version.py
kiox/batch_factory.py
kiox/episode.py
kiox/io.py
kiox/item.py
kiox/kiox.py
kiox/offline.py
kiox/shortcut.py
kiox/step.py
kiox/step_collector.py
kiox/transition.py
kiox/transition_buffer.py
kiox/transition_factory.py
kiox/distributed/__init__.py
kiox/distributed/server.py
kiox/distributed/shared_array.py
kiox/distributed/shared_batch_factory.py
kiox/distributed/step_sender.py
kiox/distributed/utility.py
kiox/distributed/proto/__init__.py
kiox/distributed/proto/step_pb2.py
kiox/distributed/proto/step_pb2_grpc.py
kiox-0.1.0.dist-info/LICENSE
kiox-0.1.0.dist-info/METADATA
kiox-0.1.0.dist-info/WHEEL
kiox-0.1.0.dist-info/top_level.txt
kiox-0.1.0.dist-info/zip-safe
kiox-0.1.0.dist-info/RECORD
