Metadata-Version: 2.1
Name: kiox
Version: 0.1.0
Summary: A composable experience replay buffer library
Home-page: https://github.com/takuseno/kiox
Author: Takuma Seno
Author-email: takuma.seno@gmail.com
License: MIT License
Platform: UNKNOWN
Classifier: Development Status :: 4 - Beta
Classifier: Intended Audience :: Developers
Classifier: Intended Audience :: Education
Classifier: Intended Audience :: Science/Research
Classifier: Topic :: Scientific/Engineering
Classifier: Topic :: Scientific/Engineering :: Artificial Intelligence
Classifier: Programming Language :: Python :: 3.7
Classifier: Programming Language :: Python :: 3.8
Classifier: Programming Language :: Python :: Implementation :: CPython
Classifier: Operating System :: POSIX :: Linux
Classifier: Operating System :: Microsoft :: Windows
Classifier: Operating System :: MacOS :: MacOS X
Requires-Python: >=3.7.0
Requires-Dist: numpy
Requires-Dist: h5py
Requires-Dist: typing-extensions
Requires-Dist: grpcio
